python_prtree-0.6.1.dist-info/RECORD
python_prtree-0.6.1.dist-info/LICENSE
python_prtree-0.6.1.dist-info/WHEEL
python_prtree-0.6.1.dist-info/top_level.txt
python_prtree-0.6.1.dist-info/METADATA
python_prtree/__init__.py
python_prtree/PRTree.cpython-39-darwin.so
