Metadata-Version: 2.1
Name: python-prtree
Version: 0.6.1
Summary: Python implementation of Priority R-Tree
Home-page: https://github.com/atksh/python_prtree
Author: atksh
License: MIT
Keywords: priority-rtree r-tree prtree rtree pybind11
Platform: UNKNOWN
Classifier: License :: OSI Approved :: MIT License
Classifier: Programming Language :: Python :: 3
Classifier: Programming Language :: Python :: 3.8
Classifier: Programming Language :: Python :: 3.9
Classifier: Programming Language :: Python :: 3.10
Classifier: Programming Language :: Python :: 3.11
Classifier: Programming Language :: Python :: 3.12
License-File: LICENSE
Requires-Dist: numpy (<2.0,>=1.16)
